NiukeCGongchengshiGangweiQiuzhiJingyanFenxiang20212022Fix1/README.md
NiukeCGongchengshiGangweiQiuzhiJingyanFenxiang20212022Fix1/__init__.py
NiukeCGongchengshiGangweiQiuzhiJingyanFenxiang20212022Fix1/__main__.py
NiukeCGongchengshiGangweiQiuzhiJingyanFenxiang20212022Fix1/file.epub
NiukeCGongchengshiGangweiQiuzhiJingyanFenxiang20212022Fix1/index.html
NiukeCGongchengshiGangweiQiuzhiJingyanFenxiang20212022Fix1/css/__init__.py
NiukeCGongchengshiGangweiQiuzhiJingyanFenxiang20212022Fix1/css/annotations.css
NiukeCGongchengshiGangweiQiuzhiJingyanFenxiang20212022Fix1/css/main.css
NiukeCGongchengshiGangweiQiuzhiJingyanFenxiang20212022Fix1/css/normalize.css
NiukeCGongchengshiGangweiQiuzhiJingyanFenxiang20212022Fix1/css/popup.css
NiukeCGongchengshiGangweiQiuzhiJingyanFenxiang20212022Fix1/font/__init__.py
NiukeCGongchengshiGangweiQiuzhiJingyanFenxiang20212022Fix1/font/fontello.eot
NiukeCGongchengshiGangweiQiuzhiJingyanFenxiang20212022Fix1/font/fontello.svg
NiukeCGongchengshiGangweiQiuzhiJingyanFenxiang20212022Fix1/font/fontello.ttf
NiukeCGongchengshiGangweiQiuzhiJingyanFenxiang20212022Fix1/font/fontello.woff
NiukeCGongchengshiGangweiQiuzhiJingyanFenxiang20212022Fix1/img/__init__.py
NiukeCGongchengshiGangweiQiuzhiJingyanFenxiang20212022Fix1/img/annotator-glyph-sprite.png
NiukeCGongchengshiGangweiQiuzhiJingyanFenxiang20212022Fix1/img/annotator-icon-sprite.png
NiukeCGongchengshiGangweiQiuzhiJingyanFenxiang20212022Fix1/img/apple-touch-icon.png
NiukeCGongchengshiGangweiQiuzhiJingyanFenxiang20212022Fix1/img/cancelfullscreen.png
NiukeCGongchengshiGangweiQiuzhiJingyanFenxiang20212022Fix1/img/close.png
NiukeCGongchengshiGangweiQiuzhiJingyanFenxiang20212022Fix1/img/fullscreen.png
NiukeCGongchengshiGangweiQiuzhiJingyanFenxiang20212022Fix1/img/loader.gif
NiukeCGongchengshiGangweiQiuzhiJingyanFenxiang20212022Fix1/img/menu-icon.png
NiukeCGongchengshiGangweiQiuzhiJingyanFenxiang20212022Fix1/img/save.png
NiukeCGongchengshiGangweiQiuzhiJingyanFenxiang20212022Fix1/img/saved.png
niuke_c_gongchengshi_gangwei_qiuzhi_jingyan_fenxiang_2021_2022_fix1-2025.3.25.0.dist-info/METADATA
niuke_c_gongchengshi_gangwei_qiuzhi_jingyan_fenxiang_2021_2022_fix1-2025.3.25.0.dist-info/WHEEL
niuke_c_gongchengshi_gangwei_qiuzhi_jingyan_fenxiang_2021_2022_fix1-2025.3.25.0.dist-info/entry_points.txt
niuke_c_gongchengshi_gangwei_qiuzhi_jingyan_fenxiang_2021_2022_fix1-2025.3.25.0.dist-info/top_level.txt
niuke_c_gongchengshi_gangwei_qiuzhi_jingyan_fenxiang_2021_2022_fix1-2025.3.25.0.dist-info/RECORD
